MANIFEST.in
README.md
setup.py
django_jstree_widget.egg-info/PKG-INFO
django_jstree_widget.egg-info/SOURCES.txt
django_jstree_widget.egg-info/dependency_links.txt
django_jstree_widget.egg-info/top_level.txt
jstree/__init__.py
jstree/apps.py
jstree/widgets.py
jstree/static/jstree/css/themes/default/32px.png
jstree/static/jstree/css/themes/default/40px.png
jstree/static/jstree/css/themes/default/style.css
jstree/static/jstree/css/themes/default/style.min.css
jstree/static/jstree/css/themes/default/throbber.gif
jstree/static/jstree/css/themes/default-dark/32px.png
jstree/static/jstree/css/themes/default-dark/40px.png
jstree/static/jstree/css/themes/default-dark/style.css
jstree/static/jstree/css/themes/default-dark/style.min.css
jstree/static/jstree/css/themes/default-dark/throbber.gif
jstree/static/jstree/js/jstree.js
jstree/static/jstree/js/jstree.min.js
jstree/templates/jstree/jstree.html
jstree/tests/__init__.py
jstree/tests/test_widgets.py