Metadata-Version: 1.0
Name: django-jstree-widget
Version: 1.0.2
Summary: Customizable widget to serve jstree with django.
Home-page: UNKNOWN
Author: Jean-Etienne Castagnede
Author-email: j.e.castagnede@gmail.com
License: MIT License
